sdif_toolkit/__init__.py
sdif_toolkit/io.py
sdif_toolkit/records.py
sdif_toolkit/time.py
sdif_toolkit-0.1.7.dist-info/LICENSE
sdif_toolkit-0.1.7.dist-info/METADATA
sdif_toolkit-0.1.7.dist-info/WHEEL
sdif_toolkit-0.1.7.dist-info/top_level.txt
sdif_toolkit-0.1.7.dist-info/RECORD
