Metadata-Version: 2.1
Name: sdif-toolkit
Version: 0.1.7
Summary: Utility to read and process swimming data files
Author-email: Colin Mothersead <cmothersead@gmail.com>
License: MIT License
Project-URL: Homepage, https://github.com/cmothersead/sdif-toolkit
Project-URL: Bug Tracker, https://github.com/cmothersead/sdif-toolkit/issues
Classifier: Programming Language :: Python :: 3
Classifier: License :: OSI Approved :: MIT License
Classifier: Operating System :: OS Independent
Requires-Python: >=3.10
License-File: LICENSE
Requires-Dist: pyodbc
